deepfox/__init__.py
deepfox/cli.py
deepfox/agents/base.py
deepfox/agents/runner.py
deepfox/agents/simple_openai_agent.py
deepfox/core/__init__.py
deepfox/core/base_protocol.py
deepfox/core/base_protocol_adapter.py
deepfox/core/client.py
deepfox/core/connector.py
deepfox/core/network.py
deepfox/core/system_commands.py
deepfox/launchers/__init__.py
deepfox/launchers/discovery_connector.py
deepfox/launchers/network_launcher.py
deepfox/launchers/terminal_console.py
deepfox/models/__init__.py
deepfox/models/manifest.py
deepfox/models/message_thread.py
deepfox/models/messages.py
deepfox/models/network_config.py
deepfox/models/network_profile.py
deepfox/models/tool.py
deepfox/protocols/__init__.py
deepfox/protocols/communication/__init__.py
deepfox/protocols/communication/simple_messaging/__init__.py
deepfox/protocols/communication/simple_messaging/adapter.py
deepfox/protocols/communication/simple_messaging/protocol.py
deepfox/protocols/discovery/__init__.py
deepfox/protocols/discovery/agent_discovery/__init__.py
deepfox/protocols/discovery/agent_discovery/adapter.py
deepfox/protocols/discovery/agent_discovery/protocol.py
deepfox/utils/__init__.py
deepfox/utils/message_util.py
deepfox/utils/network_discovey.py
deepfox/utils/protocol_loaders.py
deepfox-0.4.0.dist-info/licenses/LICENSE
deepfox-0.4.0.dist-info/METADATA
deepfox-0.4.0.dist-info/WHEEL
deepfox-0.4.0.dist-info/entry_points.txt
deepfox-0.4.0.dist-info/top_level.txt
deepfox-0.4.0.dist-info/RECORD
